dduk/__init__.py
dduk/__main__.py
dduk/process/__init__.py
dduk/process/__main__.py
dduk/process/processinfo.py
dduk/process/processmanager.py
dduk_process-0.0.6.dist-info/LICENSE
dduk_process-0.0.6.dist-info/METADATA
dduk_process-0.0.6.dist-info/WHEEL
dduk_process-0.0.6.dist-info/top_level.txt
dduk_process-0.0.6.dist-info/RECORD
